{
  "_comment": "한국어 선수명 -> 추정 시장가치 (단위: 억원). 2025-26 시즌 추정. 키는 네이버 스포츠 표기 그대로. Transfermarkt 기준 환산.",

  "_arsenal": "Arsenal FC",
  "다비드 라야": 400,
  "케파 아리사발라가": 100,
  "토미 셋포드": 100,
  "윌리엄 살리바": 1900,
  "가브리엘 마갈량이스": 1100,
  "가브리엘 마갈량이스 산투스": 1100,
  "유리엔 팀버": 800,
  "벤 화이트": 600,
  "리카르도 칼라피오리": 700,
  "피에로 힌카피에": 600,
  "크리스티안 모스케라": 600,
  "야쿠브 키비오르": 600,
  "케렐레인 모스케라": 600,
  "마일스 루이스 스켈리": 500,
  "올렉산드르 진첸코": 200,
  "데클란 라이스": 1500,
  "마르틴 외데고르": 1500,
  "마르틴 주비멘디": 1100,
  "미켈 메리노": 700,
  "카이 하베르츠": 900,
  "이선 은와네리": 700,
  "크리스티안 뇌가르": 350,
  "부카요 사카": 2200,
  "가브리엘 마르티넬리": 1000,
  "빅토르 요케레스": 1100,
  "비오케레스": 1100,
  "에베레치 에제": 1100,
  "노니 마두에케": 700,
  "레안드로 트로사르": 400,
  "가브리엘 제수스": 400,
  "라힘 스털링": 200,

  "_mancity": "Manchester City FC",
  "에데르송 모라이스": 400,
  "에데르송": 400,
  "잔루이지 돈나룸마": 600,
  "슈테판 오르테가": 100,
  "마커스 베티넬리": 50,
  "제임스 트래포드": 200,
  "후벵 디아스": 1100,
  "존 스톤스": 400,
  "네이선 아케": 400,
  "마누엘 아칸지": 700,
  "요슈코 그바르디올": 1100,
  "라얀 아이트-누리": 700,
  "라얀 아이트 누리": 700,
  "니코 오라일리": 600,
  "마테우스 누네스": 400,
  "압두코디르 쿠사노프": 350,
  "로드리": 1500,
  "베르나르도 실바": 700,
  "마테오 코바치치": 350,
  "필 포든": 1900,
  "라이얀 셰르키": 800,
  "라얀 셰르키": 800,
  "제레미 도쿠": 1100,
  "사비우": 800,
  "사비뉴": 800,
  "오마르 마르무시": 700,
  "엘링 홀란": 2400,
  "엘링 홀란드": 2400,
  "니코 곤살레스": 700,
  "티자니 레이인더스": 1100,
  "티야니 레인더르스": 1100,
  "일카이 귄도안": 100,
  "마르크 게히": 700,
  "케빈 데 브라위너": 350,
  "잭 그릴리시": 400,

  "_manunited": "Manchester United FC",
  "안드레 오나나": 300,
  "알타이 바이은드르": 250,
  "톰 히턴": 30,
  "마테우스 쿠냐": 1100,
  "베냐민 셰슈코": 1100,
  "벤야민 셰스코": 1100,
  "브라이언 음뵈모": 800,
  "조슈아 지르크지": 500,
  "라스무스 호일룬": 600,
  "라스무스 호이룬드": 600,
  "마커스 래시포드": 700,
  "알레한드로 가르나초": 1100,
  "아마드 디알로": 800,
  "아마드 디알루": 800,
  "브루노 페르난데스": 750,
  "케이시 마운트": 350,
  "메이슨 마운트": 350,
  "마누엘 우가르테": 600,
  "코비 마이누": 700,
  "디오구 달롯": 600,
  "리산드로 마르티네스": 600,
  "해리 매과이어": 200,
  "마타이스 더 리흐트": 600,
  "마티아스 더 리흐트": 600,
  "레니 요로": 700,
  "리니 요로": 700,
  "노우사이르 마즈라위": 350,
  "패트릭 도르구": 350,
  "디오구 달로트": 600,
  "타일러 프레덕슨": 100,

  "_liverpool": "Liverpool FC",
  "알리송 베커": 400,
  "기오르기 마마르다슈빌리": 700,
  "프레디 우드만": 50,
  "아르민 페치": 200,
  "버질 반 다이크": 250,
  "버질 판 데이크": 250,
  "이브라히마 코나테": 700,
  "조 고메즈": 350,
  "조반니 레오니": 700,
  "밀로스 케르케즈": 700,
  "앤디 로버트슨": 250,
  "코너 브래들리": 700,
  "제레미 프림퐁": 700,
  "예레미 프림퐁": 700,
  "라이언 흐라벤버르흐": 800,
  "리언 흐라벤버르흐": 800,
  "알렉시스 맥 앨리스터": 1500,
  "도미니크 소보슬러이": 1100,
  "쇼보슬라이": 1100,
  "커티스 존스": 700,
  "엔도 와타루": 200,
  "와타루 엔도": 200,
  "스테판 바이체치치": 500,
  "트레이 뇨니": 350,
  "플로리앙 비르츠": 2400,
  "플로리안 비르츠": 2400,
  "모하메드 살라": 800,
  "코디 각포": 1000,
  "코디 학포": 1000,
  "루이스 디아스": 1100,
  "페데리코 키에사": 350,
  "다윈 누녜스": 700,
  "우고 에키티케": 1100,
  "알렉산더 이삭": 1500,
  "트렌트 알렉산더-아놀드": 1500,
  "트렌트 알렉산더 아놀드": 1500,
  "조엘 마티프": 50,
  "버질 판 다이크": 250,

  "_tottenham": "Tottenham Hotspur FC",
  "쿨리엘모 비카리오": 350,
  "굴리엘모 비카리오": 350,
  "안토닌 킨스키": 200,
  "브렌단 오스틴": 30,
  "크리스티안 로메로": 800,
  "미키 판 더 펜": 1100,
  "라두 드라구신": 250,
  "케빈 단소": 350,
  "벤 데이비스": 150,
  "데스티니 우도기": 1100,
  "페드로 포로": 500,
  "지드 스펜스": 300,
  "제드 스펜스": 300,
  "아치 그레이": 500,
  "주앙 팔리냐": 700,
  "이브 비수마": 350,
  "파페 마타르 사르": 500,
  "로드리고 벤탄쿠르": 500,
  "루카스 베리발": 700,
  "데얀 쿨루셉스키": 700,
  "데안 쿨루셰프스키": 700,
  "자비 시몬스": 1100,
  "제임스 매디슨": 700,
  "모하메드 쿠두스": 750,
  "윌슨 오도베르": 400,
  "마노르 솔로몬": 350,
  "히샬리송": 600,
  "히샬리손": 600,
  "도미니크 솔란케": 700,
  "마티스 텔": 500,
  "랑달 콜로 무아니": 600,
  "다카이 고타": 350,
  "고타 다카이": 350,
  "코너 갤러거": 700,
  "루카 부스코비치": 250,
  "소우자": 350,

  "_chelsea": "Chelsea FC",
  "로베르트 산체스": 250,
  "필립 욜겐센": 300,
  "마이크 펜너": 50,
  "레비 콜윌": 700,
  "베노이트 바디아실리": 400,
  "베누아 바디아실리": 400,
  "토신 아다라바이오요": 250,
  "투오신": 250,
  "웨슬리 포파나": 350,
  "마크 쿠쿠렐라": 700,
  "리스 제임스": 500,
  "말로 구스토": 600,
  "주레우 안드레이": 350,
  "주레르": 350,
  "모이세스 카이세도": 1500,
  "엔조 페르난데스": 1100,
  "로메오 라비아": 350,
  "안드레이 산토스": 500,
  "다리오 에세고": 350,
  "콜 파머": 2700,
  "주앙 펠릭스": 350,
  "조앙 펠릭스": 350,
  "페드로 네토": 700,
  "노니 마두에케 첼시": 0,
  "타이리크 조지": 350,
  "잭슨 페어차일드": 100,
  "에스테방 윌리안": 700,
  "에스테반": 700,
  "니콜라스 잭슨": 700,
  "리암 델랍": 600,
  "마르크 기우": 250,
  "크리스토퍼 은쿤쿠": 350,

  "_astonvilla": "Aston Villa FC",
  "에민 디무지오": 30,
  "마르코 비조": 100,
  "마티 캐시": 350,
  "에즈리 콘사": 600,
  "파우 토레스": 350,
  "타이런 밍스": 100,
  "이안 마트센": 350,
  "루카스 디뉴": 200,
  "유리 틸레만스": 400,
  "보우비 카마라": 700,
  "아마두 오나나": 600,
  "존 매긴": 400,
  "유서프 샤비": 250,
  "엘리어트 앤더슨": 500,
  "에밀리아노 부엔디아": 200,
  "올리 왓킨스": 700,
  "도니얼 말렌": 350,
  "마르쿠스 라시포드": 700,
  "에반 게사": 200,
  "주마노이 파일레": 200,
  "에밀리아노 마르티네스": 200,
  "마르코 부엔디아": 200,

  "_newcastle": "Newcastle United FC",
  "닉 포프": 200,
  "마틴 두브라브카": 100,
  "스벤 보트만": 350,
  "파비안 셰어": 100,
  "야말 라셀스": 100,
  "다니 부르": 250,
  "키어런 트리피어": 100,
  "발렌티노 리브라멘토": 400,
  "마누엘 카밍가": 200,
  "티노 리브라멘토": 400,
  "산드로 토날리": 700,
  "조엘린튼": 350,
  "브루노 기마랑이스": 800,
  "브루노 기마라에스": 800,
  "조 윌록": 250,
  "션디 캐설": 100,
  "루이스 마일리": 400,
  "야쿠브 라믈루카": 50,
  "안소니 고든": 700,
  "하비 반스": 350,
  "윌리암 오술라": 250,
  "닉 워번": 100,

  "_bournemouth": "AFC Bournemouth",
  "조르지 페트로비치": 100,
  "케페렌 켈리허": 100,
  "디안 더후팅": 100,
  "마르코스 세네시": 400,
  "일리아 자바르니": 600,
  "딘 후이센": 1500,
  "아디 스미트": 250,
  "밀로스 케르케즈 본머스": 0,
  "후스토 모로": 250,
  "막스 아론스": 200,
  "타일러 애덤스": 200,
  "알렉스 스콧": 350,
  "라이언 크리스티": 100,
  "마커스 타베르니어": 200,
  "안토니에 세메뇨": 400,
  "안토안 세메니오": 400,
  "에반일손": 350,
  "다비드 브룩스": 100,
  "엘리 정켈": 30,

  "_barcelona": "FC Barcelona",
  "마르크-안드레 테어 슈테겐": 200,
  "보이체흐 슈쳉스니": 100,
  "보이체흐 슈첸스니": 100,
  "주안 가르시아": 350,
  "이냐키 페냐": 100,
  "파우 쿠바르시": 1100,
  "로날드 아라우호": 600,
  "안드레아스 크리스텐센": 200,
  "줄스 쿤데": 1100,
  "에리크 가르시아": 350,
  "헤라르드 마르틴": 200,
  "알레한드로 발데": 600,
  "발데": 600,
  "프란 가르시아 바르사": 200,
  "프렝키 더 용": 700,
  "프렝키 데 용": 700,
  "페드리": 2200,
  "가비": 1500,
  "다니 올모": 1100,
  "마르크 카사도": 350,
  "마르크 베르날": 350,
  "페르민 로페스": 800,
  "라민 야말": 2700,
  "하피냐": 1100,
  "라피냐": 1100,
  "페란 토레스": 700,
  "로베르트 레반도프스키": 350,
  "마르쿠스 라슈포드": 700,
  "마르쿠스 래시포드 바르사": 0,
  "루니 바르드그지": 250,

  "_realmadrid": "Real Madrid CF",
  "티보 쿠르투아": 400,
  "안드리 루닌": 350,
  "다니 카르바할": 200,
  "에데르 밀리탕": 800,
  "라울 아센시오": 350,
  "다비드 알라바": 200,
  "안토니오 뤼디거": 350,
  "안토니오 뤼디히": 350,
  "딘 후이센 마드리드": 0,
  "알바로 카레라스": 600,
  "페를랑 멘디": 200,
  "트렌트 알렉산더-아놀드 마드리드": 0,
  "프란 가르시아 레알": 200,
  "오렐리앙 추아메니": 1100,
  "에두아르도 카마빙가": 1100,
  "페데리코 발베르데": 1500,
  "주드 벨링엄": 2400,
  "아르다 귈러": 700,
  "다니 세바요스": 200,
  "브라힘 디아스": 350,
  "비니시우스 주니오르": 2700,
  "비니시우스 주니어": 2700,
  "킬리안 음바페": 2200,
  "킬리앙 음바페": 2200,
  "호드리구": 1500,
  "엔드릭": 600,
  "곤살로 가르시아": 600,
  "프랑코 마스탄투오노": 700,

  "_atletico": "Atletico Madrid",
  "얀 오블락": 300,
  "후안 무소": 100,
  "호세 마리아 히메네스": 250,
  "히메네스": 250,
  "로빈 르 노르망": 400,
  "마리오 에르모소": 200,
  "다비드 한초": 200,
  "클레망 랑글레": 100,
  "라인이르 카르도소": 200,
  "마르코스 요렌테": 350,
  "사뮈엘 리노": 800,
  "코크": 100,
  "콘도그비아": 100,
  "팡 데 파울": 350,
  "로드리고 데 파울": 350,
  "콘너 갈라거 아틀레티코": 0,
  "코너 갈라거": 700,
  "악셀 비첼": 100,
  "안투안 그리즈만": 200,
  "줄리안 알바레스": 1500,
  "훌리안 알바레스": 1500,
  "알렉산드르 쇠르로트": 800,
  "안헬 코레아": 250,
  "조반니 시메오네": 400,
  "토마스 르마": 100,
  "주앙 펠릭스 아틀레티코": 0,
  "알렉스 바에나": 600,
  "조니 카르도소": 350,
  "조니": 350,

  "_realbetis": "Real Betis Balompié",
  "이스코": 250,
  "헤르만 페수에야": 100,
  "나탄 더 소우자": 350,
  "디에고 야이네스": 100,
  "마르크 바르트라": 100,
  "에치키 페레스": 100,
  "후니오르 피르포": 200,
  "기도 로드리게스": 200,
  "조니 카르도소 베티스": 0,
  "세르히 알트미라": 100,
  "파블로 포르날스": 200,
  "조반니 로 셀소": 200,
  "안토니": 350,
  "엑토르 베예린": 100,
  "아브데 에잘잘리": 350,
  "체디라": 100,
  "쿠코 마르티네스": 100,
  "쿠쿠 마르티네스": 100,
  "셀소 보르헤스": 50,
  "비탈 누네스": 200,

  "_athleticbilbao": "Athletic Club",
  "우나이 시몬": 250,
  "훌렌 아기레사발라": 200,
  "다니 비비안": 350,
  "옌 마르티네스": 250,
  "에이마릭 라포르트": 200,
  "라포르트": 200,
  "유리 베르치체": 200,
  "오스카 데 마르코스": 50,
  "안데르 에레라": 50,
  "오이안 산세트": 600,
  "오이한 산세트": 600,
  "베냐트 프라도스": 350,
  "미켈 베르차마": 200,
  "미켈 베르차마 베티스": 0,
  "이냐키 윌리암스": 250,
  "이냐키 윌리엄스": 250,
  "니코 윌리암스": 1100,
  "니코 윌리엄스": 1100,
  "고르카 구루세타": 250,
  "이냐키 페냐 아틀레틱": 0,
  "알렉스 베렝게르": 100,

  "_realsociedad": "Real Sociedad de Fútbol",
  "알렉스 레미로": 200,
  "우나이 마레로": 50,
  "이고르 수베엘디아": 100,
  "아릿츠 엘루스톤도": 50,
  "하미라우": 100,
  "아이엔 무뇨스": 200,
  "하비에르 갈란": 100,
  "베니야트 투리엔테스": 200,
  "마르틴 주비메니 소시": 0,
  "후공이": 50,
  "브라이스 멘데스": 200,
  "타카에 쿠보": 600,
  "쿠보 다케후사": 600,
  "다케후사 쿠보": 600,
  "안데르 바레네체아": 350,
  "안데르 바렌네체아": 350,
  "미켈 오야르사발": 500,
  "셰라르드 베세이로": 100,
  "우마르 사디크": 100,
  "베니야트 마린": 100,
  "주안미": 50,

  "_celta": "RC Celta de Vigo",
  "비센테 게이타": 100,
  "이반 빌라르": 50,
  "마누 페르난데스": 100,
  "오스카 미겔레스": 50,
  "유리 베르치체 셀타": 0,
  "마르코스 알론소": 50,
  "오스카르 미겔레스": 50,
  "야르노 모리바": 100,
  "이반 살바도르": 50,
  "프란 벨트란": 100,
  "윌리 카이푸타": 50,
  "보르하 이글레시아스": 100,
  "이아고 아스파스": 100,
  "오스카르 미게에스": 100,
  "프란코 세르비": 50,
  "알폰소 곤살레스": 50,
  "오스카르 미니엘리스": 50,
  "도밍고스 두아르치": 100,

  "_villarreal": "Villarreal CF",
  "디에고 콘데": 30,
  "루이즈 주니오르": 50,
  "헤로니모 룰리": 50,
  "라울 알비올": 50,
  "후안 포이드": 50,
  "산티 코메사냐": 200,
  "에리크 바이이": 50,
  "후안 포요스": 50,
  "후안 포이트": 50,
  "후안 폴리스": 50,
  "후안 폴리": 50,
  "에티엔 카포우에": 50,
  "다니 파레호": 100,
  "산티아고 코메사냐": 100,
  "토마스 파르티": 200,
  "알베르토 모레노": 30,
  "알렉스 바에나 비야레알": 0,
  "일리아 자바르니 비야레알": 0,
  "닉 쿠노": 100,
  "닉 쿤하": 100,
  "다니 페레": 50,
  "헤라르 모레노": 200,
  "헤라르드 모레노": 200,
  "타니 올루와세이": 200,
  "타니 올루와세이 비야레알": 0,
  "토마스 페렐로": 50,
  "에티엔 카푸": 50,
  "이반 일리치": 200,
  "솔리 마르체스": 200,
  "사뮈엘 추쿠웨제": 350,
  "니콜라스 펠리스트리": 200,
  "타니 올루세이": 200,

  "_bayern": "FC Bayern München",
  "마누엘 노이어": 100,
  "스벤 울라이히": 30,
  "다니엘 페어": 100,
  "조나스 우르비히": 200,
  "조나단 타": 400,
  "다요트 우파메카노": 700,
  "김민재": 600,
  "민재 김": 600,
  "라파엘 게레이로": 200,
  "이토 히로키": 500,
  "히로키 이토": 500,
  "사샤 보이": 100,
  "알폰소 데이비스": 1100,
  "콘라드 라이머": 400,
  "요시프 스타니시치": 350,
  "조슈아 키미히": 700,
  "조슈아 키미흐": 700,
  "레온 고레츠카": 200,
  "알렉산다르 파블로비치": 500,
  "톰 비쇼프": 700,
  "올렉산드르 진첸코 바이언": 0,
  "주앙 팔리냐 바이언": 0,
  "마이클 올리세": 1100,
  "킹슬리 코망": 700,
  "세르지 그나브리": 350,
  "세르지 나브리": 350,
  "자말 무시알라": 2700,
  "루이스 디아스 바이언": 0,
  "해리 케인": 1200,
  "니콜라 잭슨": 700,
  "마티스 텔 바이언": 0,

  "_dortmund": "Borussia Dortmund",
  "그레고르 코벨": 350,
  "알렉산더 마이어": 50,
  "니클라스 쥘레": 200,
  "니코 슐로터베크": 350,
  "발데마르 안톤": 200,
  "라몬 벤제마": 350,
  "라몬 외르츠 벤제마": 350,
  "예시 벤사이드": 50,
  "다니엘 스벤손": 250,
  "야니 코우토": 350,
  "필리포 만": 250,
  "엠레 칸": 250,
  "에므레 칸": 250,
  "파스칼 그로스": 200,
  "줄리안 브란트": 500,
  "펠릭스 은무에차": 250,
  "마첼 자비처": 200,
  "막시밀리안 바이어": 350,
  "필리포 차파-피카": 350,
  "필립 차파 피카": 350,
  "카림 아데예미": 700,
  "맥시밀리언 바이어": 350,
  "세르후 기라시": 1100,
  "지오반니 레예스": 250,
  "지오반니 레이나": 250,
  "다니엘 스벤손 도르트": 0,
  "야미로 외르스만": 100,
  "야미로 외스만": 100,
  "사미 셀라이크": 100,

  "_leverkusen": "Bayer 04 Leverkusen",
  "마크 플레켄": 200,
  "마테이 코바르": 200,
  "조나단 타 레버": 0,
  "에드몬 탑소바": 600,
  "라민 베크르": 200,
  "엑사난 셰크": 700,
  "에준 셰크": 700,
  "노르디 무키엘레": 250,
  "알레한드로 그리말도": 700,
  "아르투르": 200,
  "그라니트 자카": 350,
  "에세키엘 팔라시오스": 700,
  "엑세키엘 팔라시오스": 700,
  "엘리에세르 마요르가": 100,
  "말리크 틸만": 250,
  "엘리아스 칸": 100,
  "패트릭 시크": 400,
  "마틴 테리어": 200,
  "에르네스트 포쿠": 100,
  "재럴 콴사": 250,
  "에키타이케 레버": 0,

  "_leipzig": "RB Leipzig",
  "마르틴 굴라크시": 100,
  "페테르 굴라치": 100,
  "마르틴 굴라시": 100,
  "굴라치": 100,
  "마티외 카로뉘": 30,
  "빌리 오르반": 200,
  "엘 차드일레": 200,
  "엘 차다일레 비테샤": 200,
  "카스텔로 루케바": 600,
  "다비드 라움": 400,
  "리도르 클라이먼": 100,
  "벤야민 헨릭스": 100,
  "아르투르 베르멜렌": 200,
  "케빈 칸팡가": 200,
  "사이디 디아라": 200,
  "다니 올모 라이프치히": 0,
  "사비 시몬스": 1100,
  "자비 시몬스 라이프치히": 0,
  "안톤 쿠어즈": 100,
  "쥐타 리시카-올라데": 100,
  "케빈 음바부": 100,
  "벤야민 셰스코 라이프치히": 0,
  "로이스 오펜다": 700,
  "유수프 포울센": 50,
  "크리스토프 바움가르트너": 250,

  "_stuttgart": "VfB Stuttgart",
  "알렉산더 뉘벨": 250,
  "프란르 비외르스마": 30,
  "제프 첸드라": 30,
  "지라트 마빌": 250,
  "베니야트 데미로비치": 200,
  "안소니 룬": 350,
  "안토니 룬": 350,
  "지라트": 250,
  "발도 콘데": 100,
  "안젤로 슈티에르": 250,
  "막시밀리안 미텔슈테트": 250,
  "라모 슈티에르": 100,
  "안젤로": 250,
  "엔초 밀로": 200,
  "엔조 밀로": 200,
  "아탕가나 노예": 250,
  "아탕가나": 250,
  "야미르 카림 외룀": 100,
  "데이비드 페에르 셀비": 50,
  "디안 게아": 100,
  "에르마인 운다브": 400,
  "엘 베니아민 펠로비치": 250,
  "에르네스트 운다브": 250,
  "닉 보누티": 100,
  "닉 볼": 100,
  "후스토 모로 슈트트": 0,
  "딕 호이세인": 200,
  "엘 베냐민 사이베르": 50,
  "재미 레보드자": 30,
  "리아드 헤다리": 100,
  "디에리": 100,
  "달려운 마르마트": 100,
  "토마스 슈튀치": 100,

  "_frankfurt": "Eintracht Frankfurt",
  "카우아 산토스": 100,
  "옌스 그란": 100,
  "라스무스 크리스텐센": 100,
  "로빈 코흐": 250,
  "체노티": 200,
  "오리비에 망상가": 50,
  "오스카 회예룬": 200,
  "오스카 회위룬": 200,
  "나탕요 부즈": 100,
  "엘리에 시블레르": 30,
  "엘리스 셀비": 100,
  "엘리스 셀비 프랑크푸르트": 0,
  "휴고 라르손": 250,
  "에리스 우주리": 100,
  "에리스 우즈리": 100,
  "디노 토파키스": 200,
  "휴고 에키티케 프랑크푸르트": 0,
  "오마르 마르무시 프랑크푸르트": 0,
  "마리오 괴체": 100,
  "안세르 크나우프": 100,
  "지방 베이로": 100,
  "안수 우자": 200,
  "장-마테오 바신데": 250,
  "장 마테오 바신데": 250,
  "라요 윤": 100,
  "장-마티유 바신데": 250,
  "엘리에 와알": 350,
  "엘리예 와알": 350,
  "조나단 부르카르트": 250,

  "_inter": "FC Internazionale Milano",
  "얀 좀머": 200,
  "조세프 마르티네스": 100,
  "라파엘레 디 젠나로": 30,
  "벤자민 파바르": 350,
  "프란체스코 아체르비": 50,
  "스테판 더 프레이": 200,
  "스테판 데 프레이": 200,
  "알레산드로 바스토니": 1100,
  "마티외 다르미앙": 100,
  "야니 비그너리": 100,
  "매튜 다르미앙": 100,
  "페데리코 디마르코": 700,
  "페데리코 디 마르코": 700,
  "덴젤 덤프리스": 700,
  "카를루스 아우구스토": 200,
  "헨리흐 무키타리안": 100,
  "엔리히 미키타리안": 100,
  "니콜로 바렐라": 1100,
  "하칸 찰하놀루": 600,
  "하칸 찰하노을루": 600,
  "다비데 프라테시": 350,
  "피오트르 지엘린스키": 300,
  "표트르 지엘린스키": 300,
  "라우타로 마르티네스": 1500,
  "마르쿠스 튀랑": 1100,
  "메흐디 타레미": 200,
  "마르쿠스 튀람": 1100,
  "쿠얀 보니": 200,
  "안스 보니": 100,
  "안스 카를루스": 100,
  "엔도 한오": 100,
  "보니": 200,
  "안제 다이아": 50,
  "프란체스코 피오 에스포지토": 250,
  "피오 에스포지토": 250,
  "발렌틴 카르보니": 250,
  "장 루카": 100,

  "_juventus": "Juventus FC",
  "미키엘 디 그레고리오": 250,
  "마티아 페린": 50,
  "글레이슨 브레메르": 600,
  "브레메르": 600,
  "페데리코 가티": 700,
  "가티": 700,
  "다닐로": 100,
  "피에르 칼룰루": 200,
  "안드레아 캄비아소": 700,
  "케파 사벨리": 100,
  "후안 카발": 100,
  "조노 카발": 100,
  "안드레 캄비아소": 700,
  "후안 카발리": 100,
  "팀 베이아호": 200,
  "팀 베이호": 200,
  "테ungsel 캄비아소": 0,
  "후스토 모로 유베": 0,
  "테운 코프메이너르스": 600,
  "테운 코프메이너스": 600,
  "마누엘 로카텔리": 600,
  "두샨 블라호비치": 700,
  "조나탕 다비드": 600,
  "랜덜 콜로 무아니 유베": 0,
  "콘체이상": 500,
  "프랜시스코 콘체이상": 500,
  "프란시스코 콘체이상": 500,
  "케난 일디즈": 1100,
  "주앙 마리오": 250,
  "조나단 다비드": 600,
  "프랜시스코 콘셉상": 500,
  "케난 일드즈": 1100,
  "안드레아 캄비아소 유베": 700,
  "둘리스 코프메이너스": 600,
  "팀 베이슬링": 100,
  "조반니 디 그레고리오": 250,
  "베이아흐": 200,
  "랑달 콜로 무아니 유베": 0,
  "프랑시스코 콘세이상": 500,

  "_napoli": "SSC Napoli",
  "알렉스 메레트": 200,
  "엘리아 카프릴레": 200,
  "엘리아 카프리레": 200,
  "에두아르 멘디": 30,
  "라일 부온지오르노": 350,
  "아메르 라흐마니": 200,
  "후안 헤수스": 50,
  "마티외 올리베라": 200,
  "조반니 디 로렌초": 350,
  "마티외 올리베이라": 200,
  "조 고메즈 나폴리": 0,
  "노아 랑": 250,
  "다비드 네레스": 600,
  "안드레 프랑크 잠보 앙기사": 500,
  "스타니슬라프 로보트카": 700,
  "프랭크 잠보 안기사": 500,
  "스코트 맥토미네이": 700,
  "케빈 데 브라위너 나폴리": 350,
  "헤르모소": 200,
  "라스무스 호일룬 나폴리": 0,
  "빅토르 오시멘": 1100,
  "로멜루 루카쿠": 350,
  "마티아 사라시": 100,
  "엘리프 엘마스": 250,
  "마티아스 올리베라": 200,
  "흐비차 크바라츠헬리아": 1500,
  "콰레추켈리아": 1500,
  "흐비차 콰라츠켈리아": 1500,

  "_milan": "AC Milan",
  "마이크 메냥": 400,
  "토르베요른 헤지": 30,
  "피에르 칼룰루 밀란": 0,
  "스트라힌야 파블로비치": 350,
  "스트라이냐 파블로비치": 350,
  "마테오 가비아": 200,
  "테오 에르난데스": 700,
  "마우 알레슈": 200,
  "필리포 테라치아노": 200,
  "에메르송 로얄": 200,
  "알렉시스 사엘레마에커스": 250,
  "유누스 무사": 350,
  "유시 무사": 350,
  "유시 무자": 350,
  "이스마엘 베나세르": 100,
  "유리 틸레만스 밀란": 0,
  "오니스 푸도르": 30,
  "루카 모드리치": 100,
  "루카 모드리치 밀란": 100,
  "체우 풀리시치": 700,
  "크리스티앙 풀리식": 700,
  "라파엘 레앙": 1500,
  "오포로다": 50,
  "산티아고 히메네스": 350,
  "올리비에 지루": 100,
  "타미 에이브러햄": 200,
  "노아 오카포": 600,
  "노아 오쿠포": 600,
  "타미 에이브라함": 200,

  "_roma": "AS Roma",
  "미일레 스빌라르": 350,
  "밀레 스빌라르": 350,
  "마티아스 알메이다": 30,
  "마츠 후멜스": 30,
  "에반 은디카": 350,
  "주마노이 만시니": 350,
  "잔루카 만시니": 350,
  "마리오 헤르모소": 200,
  "안헬리뇨": 200,
  "조슈아 자이르츠": 100,
  "사울 늘게라": 100,
  "주코비치": 200,
  "마누엘 디브룬": 100,
  "사울": 100,
  "마티아 자레": 50,
  "엘 시아라리": 200,
  "마누 코네": 600,
  "엔조 르 페": 250,
  "엔조 르페": 250,
  "로렌초 펠레그리니": 350,
  "브라이언 크리스탄테": 200,
  "엘 시아라위": 200,
  "조반니 시미니": 100,
  "스테판 엘 샤라위": 200,
  "엘 샤라위": 200,
  "파올로 디발라": 250,
  "아르템 도브비크": 350,
  "에반 퍼거슨": 250,
  "마티아스 솔레": 350,
  "마티스 솔레": 350,
  "리카르도 피냐": 30,
  "안드레아 벨로티": 100,

  "_lazio": "SS Lazio",
  "이반 프로베델": 200,
  "엘리아 만돌리아니": 30,
  "마누엘 라차리": 100,
  "알레시오 로마뇰리": 100,
  "마리오 길라": 200,
  "엘세이드 히사이": 50,
  "노바 라브로비치": 100,
  "누노 타바리스": 250,
  "마티아스 베시노": 30,
  "마티아 자카니": 200,
  "마티아 자카그니": 200,
  "다닐로 카타르디": 250,
  "마티아 자카리아": 200,
  "닉콜로 로벨라": 200,
  "토마 게드라": 30,
  "마티아 디아": 200,
  "마티아 디아 라치오": 0,
  "디아": 200,
  "구스타프 이삭센": 250,
  "마누엘 칸셀리에리": 50,
  "타이 베즐로비치": 30,
  "보울라예 디아": 200,
  "발렌틴 카스텔라노스": 250,
  "치로 임모빌레": 50,
  "타티 카스텔라노스": 250,
  "페드로": 30,
  "마트테오 카스텔라노스": 250,
  "마티아 베시노": 30,
  "잭마우": 30,

  "_atalanta": "Atalanta BC",
  "마르코 카르네세키": 350,
  "마르크 모리지": 30,
  "이수아크 후이센": 200,
  "베리오트 히엔": 350,
  "베리아트 히엔": 350,
  "지미 카브와": 30,
  "라파 마린": 200,
  "다비드 줄리": 30,
  "다비데 잠파": 100,
  "마르텐 더 룬": 350,
  "에데르송 산타나": 250,
  "마리오 파살리치": 200,
  "마르코 브레스카닌": 100,
  "이만무엘 라텔로": 100,
  "에브렘 라텔로": 100,
  "샤를 데 케테레르": 350,
  "샤를 데 케테라이러": 350,
  "찰스 데 케테라이러": 350,
  "마티아 자파코스타": 100,
  "찰스 드 케타에레": 350,
  "마테오 레테기": 700,
  "라사르 사마르딕": 200,
  "라사르 사마르직치치": 200,
  "다비드 술레르": 250,
  "주니오르 무사": 350,

  "_fiorentina": "ACF Fiorentina",
  "다비드 데 헤아": 100,
  "다비드 데헤아": 100,
  "데헤아": 100,
  "토마소 마르티넬리": 30,
  "올리버 크리스텐센": 100,
  "도도": 100,
  "피에트로 코무초": 200,
  "마린 폰그라식": 200,
  "마티아스 비라기": 100,
  "로빈 고센스": 200,
  "롤란도 만돌라기": 100,
  "안드레아 콜파니": 250,
  "한스-마우리츠 베이저": 100,
  "한스 마우리츠 베이저": 100,
  "에딘 제코": 30,
  "모이세 켄": 1100,
  "모이세 킨": 1100,
  "알베르 굳문드손": 250,
  "알베르트 구드문손": 250,
  "리카르도 소티유": 200,
  "리카르도 사오티유": 200,

  "_psg": "Paris Saint-Germain",
  "잔루이지 돈나룸마 파리": 0,
  "마트베이 사파노프": 200,
  "루카스 슈발리에": 700,
  "주앙 네베스": 1500,
  "조앙 네베스": 1500,
  "비티니야": 1100,
  "윌리언 파초": 700,
  "마르키뉴스": 600,
  "푸엘리오 마르키뉴스": 600,
  "팀발 데시리": 500,
  "데시레 두에": 1100,
  "이강인": 600,
  "강인 이": 600,
  "케빈 단소 파리": 0,
  "팝 누사이르": 350,
  "누노 멘드스": 800,
  "누누 멘데스": 800,
  "아쉬라프 하키미": 700,
  "파비안 루이스": 600,
  "주니오르 모키": 50,
  "주크": 30,
  "워런 자이르 에므리": 1100,
  "와렌 자이르 에므리": 1100,
  "호이르고": 1500,
  "콰니 르 페": 100,
  "곤살로 라모스": 350,
  "브래들리 바르콜라": 1500,
  "우스만 뎀벨레": 1500,
  "이브라힘 음바예": 350,
  "리 강인": 600,

  "_feyenoord": "Feyenoord",
  "황인범": 200,
  "인범 황": 200,

  "_wolves": "Wolverhampton",
  "황희찬": 200,
  "희찬 황": 200,

  "_other_korean": "Other Korean players",
  "손흥민": 600,
  "흥민 손": 600,
  "이재성": 100,
  "오현규": 200,

  "_lafc_etc": "LAFC and others",
  "손흥민 LAFC": 0,
  "메시": 200,
  "리오넬 메시": 200
}
